Metadata-Version: 2.1
Name: alvonOnvif
Version: 0.0.9
Summary: Custom Onvif
Download-URL: 
Author: Deepak Singh
Keywords: opencv,onvif,alvon,stream,logging,onvif-stream
License-File: LICENSE.txt
